flpc_v2-0.3.4.dist-info/METADATA
flpc_v2-0.3.4.dist-info/WHEEL
flpc_v2-0.3.4.dist-info/licenses/LICENSE
flpc_v2/__init__.py
flpc_v2/__init__.pyi
flpc_v2/flpc_v2.cpython-314t-x86_64-linux-gnu.so
flpc_v2/py.typed
flpc_v2-0.3.4.dist-info/RECORD
