Metadata-Version: 2.4
Name: flpc_v2
Version: 0.3.4
Classifier: Programming Language :: Rust
Classifier: Programming Language :: Python :: Implementation :: CPython
Classifier: Programming Language :: Python :: Implementation :: PyPy
License-File: LICENSE
Summary: A Lightning Fast ⚡ Rust-based regex crate wrapper for Python3 to get faster performance. 👾
Maintainer-email: Adarsh Gourab Mahalik <gourabmahalikadarsh@gmail.com>
License-Expression: MIT
Requires-Python: >=3.14
